README.md
setup.py
test/test.py
text2sentences/__init__.py
text2sentences/detectlang.py
text2sentences/sentence.py
text2sentences/version.py
text2sentences.egg-info/PKG-INFO
text2sentences.egg-info/SOURCES.txt
text2sentences.egg-info/dependency_links.txt
text2sentences.egg-info/top_level.txt