Metadata-Version: 2.1
Name: text2sentences
Version: 0.0.5
Summary: convert a long text to sentences
Home-page: https://github.com/yumoqing/text2sentences
Author: Yu Moqing
Author-email: yumoqing@gmail.com
Keywords: text,sentence
Classifier: Intended Audience :: End Users/Desktop
Classifier: Intended Audience :: Developers
Classifier: Intended Audience :: Information Technology
Classifier: Intended Audience :: System Administrators
Classifier: Operating System :: OS Independent
Classifier: License :: OSI Approved :: Mozilla Public License 2.0 (MPL 2.0)
Classifier: Programming Language :: Python :: 3
